README.md
pyproject.toml
setup.py
gl_plugin/__init__.py
gl_plugin.egg-info/PKG-INFO
gl_plugin.egg-info/SOURCES.txt
gl_plugin.egg-info/dependency_links.txt
gl_plugin.egg-info/requires.txt
gl_plugin.egg-info/top_level.txt
gl_plugin/plugin/__init__.py
gl_plugin/plugin/handler.py
gl_plugin/plugin/manager.py
gl_plugin/plugin/plugin.py
gl_plugin/plugin/registry.py
gl_plugin/services/__init__.py
gl_plugin/services/config.py