Metadata-Version: 2.4
Name: gl-plugin
Version: 0.1.0
Summary: GL SDK's Plugin Architecture Implementation
Author-email: Samuel Lusandi <samuel.lusandi@gdplabs.id>
Requires-Python: <3.14,>=3.11
Requires-Dist: python-dotenv>=1.2.1
Provides-Extra: dev
Requires-Dist: pre-commit<4.0.0,>=3.6.2; extra == "dev"
Requires-Dist: pytest<9.0.0,>=8.3.4; extra == "dev"
Requires-Dist: pytest-mock<4.0.0,>=3.14.0; extra == "dev"
Requires-Dist: pytest-asyncio<1.0.0,>=0.25.3; extra == "dev"
Requires-Dist: coverage<8.0.0,>=7.6.10; extra == "dev"
Requires-Dist: mypy<2.0.0,>=1.11.2; extra == "dev"
Requires-Dist: ruff<1.0.0,>=0.9.9; extra == "dev"
Requires-Dist: pytest-cov<6.0.0,>=5.0.0; extra == "dev"
